MANIFEST.in
setup.py
GoogleCodeWikiImporter.egg-info/PKG-INFO
GoogleCodeWikiImporter.egg-info/SOURCES.txt
GoogleCodeWikiImporter.egg-info/dependency_links.txt
GoogleCodeWikiImporter.egg-info/entry_points.txt
GoogleCodeWikiImporter.egg-info/pbr.json
GoogleCodeWikiImporter.egg-info/requires.txt
GoogleCodeWikiImporter.egg-info/top_level.txt
GoogleCodeWikiImporter.egg-info/zip-safe
googlecodewikiimporter/__init__.py
googlecodewikiimporter/importer.py
googlecodewikiimporter/templates/index.html
googlecodewikiimporter/tests/__init__.py
googlecodewikiimporter/tests/test_importer.py