Metadata-Version: 1.0
Name: GoogleCodeWikiImporter
Version: 0.5.2
Summary: Google Code Wiki Importer plugin for the Allura platform
Home-page: http://sf.net/p/googlecodewikiimporter
Author: Tim Van Steenburgh
Author-email: tvansteenburgh@gmail.com
License: GPLv3
Platform: UNKNOWN
